{
	"info": {
		"_postman_id": "9e7a1c82-16cb-4831-9f5c-5cd7d6b19acf",
		"name": "FebaCapital",
		"schema": "https://schema.getpostman.com/json/collection/v2.1.0/collection.json",
		"_exporter_id": "3051335"
	},
	"item": [
		{
			"name": "Login",
			"event": [
				{
					"listen": "prerequest",
					"script": {
						"exec": [
							""
						],
						"type": "text/javascript",
						"packages": {}
					}
				},
				{
					"listen": "test",
					"script": {
						"exec": [
							"const responseJson = pm.response.json();\r",
							"const jwt = responseJson.access_token;\r",
							"\r",
							"pm.environment.set('JWT', 'Bearer ${jwt}');"
						],
						"type": "text/javascript",
						"packages": {}
					}
				}
			],
			"protocolProfileBehavior": {
				"disabledSystemHeaders": {
					"content-type": true
				}
			},
			"request": {
				"method": "POST",
				"header": [
					{
						"key": "Content-Type",
						"value": "application/json",
						"type": "text"
					}
				],
				"body": {
					"mode": "raw",
					"raw": "{\r\n    \"username\": \"ronaldo\",\r\n    \"password\": \"123456\"\r\n}",
					"options": {
						"raw": {
							"language": "json"
						}
					}
				},
				"url": {
					"raw": "http://localhost:8080/api/login",
					"protocol": "http",
					"host": [
						"localhost"
					],
					"port": "8080",
					"path": [
						"api",
						"login"
					]
				}
			},
			"response": []
		},
		{
			"name": "Criar Cliente",
			"request": {
				"auth": {
					"type": "bearer",
					"bearer": [
						{
							"key": "token",
							"value": "{{JWT}}",
							"type": "string"
						}
					]
				},
				"method": "POST",
				"header": [
					{
						"key": "Content-Type",
						"value": "application/json",
						"type": "text"
					}
				],
				"body": {
					"mode": "raw",
					"raw": "{\r\n  \"name\": \"Royal's\",\r\n  \"cpf\": \"98765432112\",\r\n  \"zipcode\": \"58297000\",\r\n  \"sex\": \"M\",\r\n  \"neighborhood\": \"Centro\"\r\n}\r\n",
					"options": {
						"raw": {
							"language": "json"
						}
					}
				},
				"url": {
					"raw": "http://localhost:8080/api/cliente",
					"protocol": "http",
					"host": [
						"localhost"
					],
					"port": "8080",
					"path": [
						"api",
						"cliente"
					]
				}
			},
			"response": []
		},
		{
			"name": "Listar Cliente",
			"protocolProfileBehavior": {
				"disableBodyPruning": true
			},
			"request": {
				"auth": {
					"type": "bearer",
					"bearer": [
						{
							"key": "token",
							"value": "{{JWT}}",
							"type": "string"
						}
					]
				},
				"method": "GET",
				"header": [
					{
						"key": "Content-Type",
						"value": "application/json",
						"type": "text"
					}
				],
				"body": {
					"mode": "raw",
					"raw": "",
					"options": {
						"raw": {
							"language": "json"
						}
					}
				},
				"url": {
					"raw": "http://localhost:8080/api/cliente?filter=123&orderBy=title&orderDirection=desc&limit=10",
					"protocol": "http",
					"host": [
						"localhost"
					],
					"port": "8080",
					"path": [
						"api",
						"cliente"
					],
					"query": [
						{
							"key": "filter",
							"value": "123"
						},
						{
							"key": "orderBy",
							"value": "title"
						},
						{
							"key": "orderDirection",
							"value": "desc"
						},
						{
							"key": "limit",
							"value": "10"
						}
					]
				}
			},
			"response": []
		},
		{
			"name": "Criar Livro",
			"request": {
				"auth": {
					"type": "bearer",
					"bearer": [
						{
							"key": "token",
							"value": "{{JWT}}",
							"type": "string"
						}
					]
				},
				"method": "POST",
				"header": [
					{
						"key": "Content-Type",
						"value": "application/json",
						"type": "text"
					}
				],
				"body": {
					"mode": "raw",
					"raw": "{\r\n  \"isbn\": \"9788535922806\",\r\n  \"title\": \"1234567891234\",\r\n  \"author\": \"1234567891234\",\r\n  \"price\": 12.5,\r\n  \"inventory\": 50\r\n}\r\n",
					"options": {
						"raw": {
							"language": "json"
						}
					}
				},
				"url": {
					"raw": "http://localhost:8080/api/livro",
					"protocol": "http",
					"host": [
						"localhost"
					],
					"port": "8080",
					"path": [
						"api",
						"livro"
					]
				}
			},
			"response": []
		},
		{
			"name": "Listar Livros",
			"protocolProfileBehavior": {
				"disableBodyPruning": true
			},
			"request": {
				"auth": {
					"type": "bearer",
					"bearer": [
						{
							"key": "token",
							"value": "{{JWT}}",
							"type": "string"
						}
					]
				},
				"method": "GET",
				"header": [
					{
						"key": "Content-Type",
						"value": "application/json",
						"type": "text"
					}
				],
				"body": {
					"mode": "raw",
					"raw": "",
					"options": {
						"raw": {
							"language": "json"
						}
					}
				},
				"url": {
					"raw": "http://localhost:8080/api/livro?filter=&orderBy=title&orderDirection=desc&limit=10",
					"protocol": "http",
					"host": [
						"localhost"
					],
					"port": "8080",
					"path": [
						"api",
						"livro"
					],
					"query": [
						{
							"key": "filter",
							"value": ""
						},
						{
							"key": "orderBy",
							"value": "title"
						},
						{
							"key": "orderDirection",
							"value": "desc"
						},
						{
							"key": "limit",
							"value": "10"
						}
					]
				}
			},
			"response": []
		}
	]
}